src/__init__.py
src/__main__.py
src/cli.py
src/fileutils.py
src/output.py
wgrep/__init__.py
wgrep/__main__.py
wgrep/cli.py
wgrep/fileutils.py
wgrep/output.py
wgrep-1.0.0.dist-info/METADATA
wgrep-1.0.0.dist-info/WHEEL
wgrep-1.0.0.dist-info/top_level.txt
wgrep-1.0.0.dist-info/RECORD
