Metadata-Version: 2.1
Name: wgrep
Version: 1.0.0
Summary: Parse whois data into program-readable formats (like JSON, XML, TOML, etc.)
Home-page: UNKNOWN
Author: callope
Author-email: callope@proton.me
License: UNKNOWN
Keywords: python,whois,lookup,api integration,information
Platform: UNKNOWN
Classifier: Development Status :: 1 - Planning
Classifier: Intended Audience :: Developers
Classifier: Programming Language :: Python :: 3
Classifier: Operating System :: Unix
Classifier: Operating System :: MacOS :: MacOS X
Classifier: Operating System :: Microsoft :: Windows
Requires-Dist: dict2xml
Requires-Dist: python-whois
Requires-Dist: toml
